Metadata-Version: 2.1
Name: tourmapper
Version: 0.1.1
Summary: Build interactive maps from GPS activity data
Home-page: https://github.com/tomfrankkirk/tourmapper
Author: Tom Kirk
Author-email: tomfrankkirk@gmail.com
License: UNKNOWN
Platform: UNKNOWN
